binance_agent/__init__.py
binance_agent-0.0.1.dist-info/licenses/LICENSE
binance_agent-0.0.1.dist-info/METADATA
binance_agent-0.0.1.dist-info/WHEEL
binance_agent-0.0.1.dist-info/top_level.txt
binance_agent-0.0.1.dist-info/RECORD
