Metadata-Version: 2.4
Name: binance-agent
Version: 0.0.1
Summary: Python library for integrating the Binance API into agentic workflows, an MCP (Model Context Protocol) implementation
Author-email: Kael Zhang <i+pypi@kael.me>
License: Copyright (c) 2013 kaelzhang <>, contributors
Project-URL: Homepage, https://github.com/kaelzhang/binance-agent
Keywords: binance-agent
Classifier: Topic :: Software Development :: Libraries :: Python Modules
Classifier: Programming Language :: Python :: 3.7
Classifier: Programming Language :: Python :: 3.8
Classifier: Programming Language :: Python :: 3.9
Classifier: Programming Language :: Python :: 3.10
Classifier: Programming Language :: Python :: 3.11
Classifier: Programming Language :: Python :: 3.12
Classifier: Programming Language :: Python :: Implementation :: PyPy
Classifier: Topic :: Software Development :: Libraries :: Python Modules
Classifier: License :: OSI Approved :: MIT License
Requires-Python: >=3.7
License-File: LICENSE
Provides-Extra: dev
Requires-Dist: coverage; extra == "dev"
Requires-Dist: ruff; extra == "dev"
Requires-Dist: pytest; extra == "dev"
Requires-Dist: pytest-cov; extra == "dev"
Requires-Dist: twine; extra == "dev"
Requires-Dist: mypy; extra == "dev"
Requires-Dist: build; extra == "dev"
Dynamic: license-file
